postgresVectorTileGenerator/__init__.py
postgresVectorTileGenerator/generator.py
postgresVectorTileGenerator-0.0.1.dist-info/METADATA
postgresVectorTileGenerator-0.0.1.dist-info/WHEEL
postgresVectorTileGenerator-0.0.1.dist-info/entry_points.txt
postgresVectorTileGenerator-0.0.1.dist-info/top_level.txt
postgresVectorTileGenerator-0.0.1.dist-info/RECORD
