Metadata-Version: 2.1
Name: postgresVectorTileGenerator
Version: 0.0.1
Summary: Automatically generate a vector tile cache for a table in postgreSQL.
Home-page: https://github.com/mkeller3/postgresVectorTileGenerator
Author: Michael Keller
Author-email: michaelkeller03@gmail.com
License: GNU General Public License v3.0
Platform: UNKNOWN
Classifier: License :: OSI Approved :: GNU General Public License v3 (GPLv3)
Classifier: Programming Language :: Python :: 3
Requires-Dist: VectorTileGenerator (==0.0.5)
Requires-Dist: psycopg2 (==2.8.4)
